nimpy/__init__.py
nimpy/nimpy.py
nimmpy-1.0.1.dist-info/METADATA
nimmpy-1.0.1.dist-info/WHEEL
nimmpy-1.0.1.dist-info/top_level.txt
nimmpy-1.0.1.dist-info/RECORD
