Metadata-Version: 2.1
Name: nimmpy
Version: 1.0.1
Summary: HeHe IT'S ME SIDHU SER
Home-page: UNKNOWN
Author: sidharth
Author-email: sidharthss2690@gmail.com
License: UNKNOWN
Platform: UNKNOWN
Classifier: Programming Language :: Python :: 3
Classifier: License :: OSI Approved :: MIT License
Classifier: Operating System :: OS Independent
Requires-Python: >=3.6
Requires-Dist: usellm
